{
  "__className__": "serverpod.DatabaseMigration",
  "actions": [
    {
      "__className__": "serverpod.DatabaseMigrationAction",
      "type": "alterTable",
      "alterTable": {
        "__className__": "serverpod.TableMigration",
        "name": "sleep_sessions",
        "schema": "public",
        "addColumns": [],
        "deleteColumns": [],
        "modifyColumns": [],
        "addIndexes": [
          {
            "__className__": "serverpod.IndexDefinition",
            "indexName": "idx_sleep_sessions_data_source",
            "elements": [
              {
                "__className__": "serverpod.IndexElementDefinition",
                "type": 0,
                "definition": "sleepDataSource"
              }
            ],
            "type": "btree",
            "isUnique": false,
            "isPrimary": false
          },
          {
            "__className__": "serverpod.IndexDefinition",
            "indexName": "idx_sleep_sessions_date_source",
            "elements": [
              {
                "__className__": "serverpod.IndexElementDefinition",
                "type": 0,
                "definition": "sessionDate"
              },
              {
                "__className__": "serverpod.IndexElementDefinition",
                "type": 0,
                "definition": "sleepDataSource"
              }
            ],
            "type": "btree",
            "isUnique": false,
            "isPrimary": false
          }
        ],
        "deleteIndexes": [],
        "addForeignKeys": [],
        "deleteForeignKeys": [],
        "warnings": []
      }
    }
  ],
  "warnings": [],
  "migrationApiVersion": 1
}